LICENSE
setup.py
luno_streams/__init__.py
luno_streams/app.html
luno_streams/app.py
luno_streams/cli.py
luno_streams/server.py
luno_streams/updater.py
luno_streams.egg-info/PKG-INFO
luno_streams.egg-info/SOURCES.txt
luno_streams.egg-info/dependency_links.txt
luno_streams.egg-info/entry_points.txt
luno_streams.egg-info/requires.txt
luno_streams.egg-info/top_level.txt