Metadata-Version: 2.1
Name: luno-streams
Version: 0.1.5
Summary: Luno client for the streaming API.
Home-page: https://github.com/jacoduplessis/luno_streams
Author: Jaco du Plessis
Author-email: jaco@jacoduplessis.co.za
License: UNKNOWN
Keywords: luno websockets
Platform: UNKNOWN
Classifier: License :: OSI Approved :: MIT License
Classifier: Programming Language :: Python :: 3
License-File: LICENSE
